magic_duckdb/__init__.py
magic_duckdb/_version.py
magic_duckdb/duckdb_mode.py
magic_duckdb/magic.py
magic_duckdb/autocomplete/__init__.py
magic_duckdb/autocomplete/autocompletion_v2.py
magic_duckdb/autocomplete/common.py
magic_duckdb/extras/__init__.py
magic_duckdb/extras/ast_graphviz.py
magic_duckdb/extras/explain_analyze_graphviz.py
magic_duckdb/extras/jinja_template.py
magic_duckdb/extras/logging_init.py
magic_duckdb/extras/sql_ai.py
magic_duckdb/extras/sqlformatter.py
magic_duckdb-0.2.3.dist-info/METADATA
magic_duckdb-0.2.3.dist-info/WHEEL
magic_duckdb-0.2.3.dist-info/licenses/LICENSE.md
magic_duckdb-0.2.3.dist-info/RECORD
