Metadata-Version: 2.4
Name: magic_duckdb
Version: 0.2.3
Summary: DuckDB Cell (%%dql) and Line (%dql) Magics for Jupyter and VSCode
Project-URL: Homepage, https://github.com/iqmo-org/magic_duckdb
Project-URL: Repository, https://github.com/iqmo-org/magic_duckdb
Project-URL: Issues, https://github.com/iqmo-org/magic_duckdb/issues
Author-email: Paul T <paul@iqmo.com>
Maintainer-email: Paul T <paul@iqmo.com>
License-Expression: BSD-3-Clause
License-File: LICENSE.md
Classifier: Programming Language :: Python :: 3.10
Classifier: Programming Language :: Python :: 3.11
Classifier: Programming Language :: Python :: 3.12
Classifier: Programming Language :: Python :: 3.13
Classifier: Programming Language :: Python :: 3.14
Requires-Python: >=3.10
Requires-Dist: duckdb>=1.2.0
Requires-Dist: ipython>=8.0.0
Requires-Dist: jinja2>=3.1.2
Requires-Dist: pandas>=2.1.2
